setup.cfg
setup.py
Ledart/ArgumentParser.py
Ledart/Artnet.py
Ledart/DeviceInterfaces.py
Ledart/Filter.py
Ledart/Lmcp.py
Ledart/__init__.py
Ledart/__main__.py
Ledart/runPatternJob.py
Ledart/stripinfo.py
Ledart/utils.py
Ledart.egg-info/PKG-INFO
Ledart.egg-info/SOURCES.txt
Ledart.egg-info/dependency_links.txt
Ledart.egg-info/not-zip-safe
Ledart.egg-info/requires.txt
Ledart.egg-info/top_level.txt
Ledart/MatrixSim/MatrixScreen.py
Ledart/MatrixSim/OpenGL-learn.py
Ledart/MatrixSim/Pixel.py
Ledart/MatrixSim/__init__.py
Ledart/MatrixSim/Interfaces/DummyInterface.py
Ledart/MatrixSim/Interfaces/Interface.py
Ledart/MatrixSim/Interfaces/OpenGlInterface.py
Ledart/MatrixSim/Interfaces/PygameInterface.py
Ledart/MatrixSim/Interfaces/__init__.py
Ledart/Patterns/Arcadia.py
Ledart/Patterns/Clock.py
Ledart/Patterns/DisplayImage.py
Ledart/Patterns/FadeMatrix.py
Ledart/Patterns/FillTest.py
Ledart/Patterns/Fire.py
Ledart/Patterns/GraphicsTests.py
Ledart/Patterns/Mandelbrot.py
Ledart/Patterns/Patterns.py
Ledart/Patterns/PixelLife.py
Ledart/Patterns/Plasma.py
Ledart/Patterns/RainPattern.py
Ledart/Patterns/Sim.py
Ledart/Patterns/Snake.py
Ledart/Patterns/TamaGotchi.py
Ledart/Patterns/Tron.py
Ledart/Patterns/VUmeter.py
Ledart/Patterns/VideoPlay.py
Ledart/Patterns/Water.py
Ledart/Patterns/__init__.py
Ledart/Patterns/sven.py
Ledart/Patterns/Life/__init__.py
Ledart/Patterns/Life/life.py
Ledart/Patterns/Pong/Pong.py
Ledart/Patterns/Pong/__init__.py
Ledart/Patterns/SuperPixelBros/SuperPixelBros.py
Ledart/Patterns/SuperPixelBros/__init__.py
Ledart/Tools/NumberSegmentBitMap.py
Ledart/Tools/Palet.py
Ledart/Tools/Timing.py
Ledart/Tools/__init__.py
Ledart/Tools/Controllers/Controllers.py
Ledart/Tools/Controllers/PygameController.py
Ledart/Tools/Controllers/SoundControllers.py
Ledart/Tools/Controllers/__init__.py
Ledart/Tools/Graphics/Colors.py
Ledart/Tools/Graphics/ConvertColors.py
Ledart/Tools/Graphics/Graphics.py
Ledart/Tools/Graphics/HSLColorTools.py
Ledart/Tools/Graphics/HSVColorTools.py
Ledart/Tools/Graphics/Imaged.py
Ledart/Tools/Graphics/RGBColorTools.py
Ledart/Tools/Graphics/Surface.py
Ledart/Tools/Graphics/__init__.py
Ledart/configs/__init__.py
