Metadata-Version: 1.1
Name: Ledart
Version: 0.3.0
Summary: led controle software.
Home-page: https://github.com/tkkrlab/py-ledart
Author: Robert van der Tuuk
Author-email: 201292@live.nl
License: GPL3
Download-URL: https://github.com/tkkrlab/py-ledart/tarbal/0.3.0
Platform: UNKNOWN
